mojo/extension/__init__.py
mojo/extension/extensionfactory.py
mojo/extension/extensionprotocol.py
mojo/extension/overridepack.py
mojo/extension/overrideprotocol.py
mojo/extension/superfactory.py
mojo/extension/utilities.py
mojo/extension/wellknown.py
mojo_extension-2.0.6.dist-info/LICENSE.txt
mojo_extension-2.0.6.dist-info/METADATA
mojo_extension-2.0.6.dist-info/WHEEL
mojo_extension-2.0.6.dist-info/RECORD
