Metadata-Version: 2.1
Name: mojo-extension
Version: 2.0.6
Summary: Automation Mojo Extension Package
Home-page: http://automationmojo.com
License: LICENSE.txt
Keywords: python
Author: Myron Walker
Author-email: myron.walker@gmail.com
Requires-Python: >=3.9,<4.0
Classifier: License :: OSI Approved :: MIT License
Classifier: License :: Other/Proprietary License
Classifier: Operating System :: POSIX
Classifier: Programming Language :: Python :: 3
Classifier: Programming Language :: Python :: 3.9
Classifier: Programming Language :: Python :: 3.10
Classifier: Programming Language :: Python :: 3.11
Classifier: Programming Language :: Python :: 3.12
Requires-Dist: mojo-collections (>=2.0.1,<2.1.0)
Requires-Dist: mojo-errors (>=2.0.0,<2.1.0)
Requires-Dist: mojo-startup (>=2.0.4,<2.1.0)
Project-URL: Repository, https://github.com/automationmojo/mojo-extension
